cf_d1_manager/__init__.py
cf_d1_manager-2025.9.14920.dist-info/licenses/LICENSE
cf_d1_manager-2025.9.14920.dist-info/METADATA
cf_d1_manager-2025.9.14920.dist-info/WHEEL
cf_d1_manager-2025.9.14920.dist-info/top_level.txt
cf_d1_manager-2025.9.14920.dist-info/RECORD
