Metadata-Version: 2.4
Name: cf_d1_manager
Version: 2025.9.14920
Summary: CF_API_TOKEN = _must_env("CF_API_TOKEN") CF_ACCOUNT_ID = _must_env("CF_ACCOUNT_ID") CF_D1_DATABASE_ID = _must_env("CF_D1_DATABASE_ID") CF_A…
Author-email: Eugene Evstafev <hi@eugene.plus>
License: MIT License
Project-URL: Repository, https://pypi.org/project/cf_d1_manager/
Requires-Python: >=3.9
License-File: LICENSE
Requires-Dist: http_exception
Dynamic: license-file
